applitools/selenium/__init__.py
applitools/selenium/__version__.py
applitools/selenium/eyes.py
applitools/selenium/object_registry.py
applitools/selenium/protocol.py
applitools/selenium/py.typed
applitools/selenium/runner.py
applitools/selenium/fluent/__init__.py
applitools/selenium/fluent/region.py
applitools/selenium/fluent/selenium_check_settings.py
applitools/selenium/fluent/target.py
applitools/selenium/fluent/target_path.py
eyes_selenium-6.4.18.dist-info/licenses/LICENSE
eyes_selenium-6.4.18.dist-info/METADATA
eyes_selenium-6.4.18.dist-info/WHEEL
eyes_selenium-6.4.18.dist-info/top_level.txt
eyes_selenium-6.4.18.dist-info/RECORD
