Metadata-Version: 2.4
Name: eyes-selenium
Version: 6.4.18
Summary: Applitools Python SDK. Selenium package
Author-email: Applitools Team <team@applitools.com>
License-Expression: LicenseRef-Proprietary
Project-URL: Homepage, https://applitools.com
Keywords: applitools,eyes,eyes_selenium
Classifier: Programming Language :: Python
Classifier: Development Status :: 5 - Production/Stable
Classifier: Intended Audience :: Developers
Classifier: Operating System :: MacOS
Classifier: Operating System :: Microsoft :: Windows
Classifier: Operating System :: POSIX :: Linux
Classifier: Topic :: Software Development :: Quality Assurance
Classifier: Topic :: Software Development :: Testing
Requires-Python: <4,>=3.7
License-File: LICENSE
Requires-Dist: Appium-Python-Client<6,>=2
Requires-Dist: eyes-common==6.5.18
Requires-Dist: selenium<5,>=4
Dynamic: license-file
